ml_csdlo6021/__init__.py
ml_csdlo6021/linear_regression.py
ml_csdlo6021/logistic_regression.py
ml_csdlo6021/multivariate_linear_regression.py
ml_csdlo6021-0.0.0.3.dist-info/LICENSE
ml_csdlo6021-0.0.0.3.dist-info/METADATA
ml_csdlo6021-0.0.0.3.dist-info/WHEEL
ml_csdlo6021-0.0.0.3.dist-info/top_level.txt
ml_csdlo6021-0.0.0.3.dist-info/RECORD
